<annotation>
	<folder>save_img</folder>
	<filename>503cd6a80f5c4949846437ba9a0be6f8.jpg.jpg</filename>
	<path>/home/huyvd/Documents/works/pytorch_tutorial/tap_code/indo_card_code/card_indo_test_step3/save_img/503cd6a80f5c4949846437ba9a0be6f8.jpg.jpg</path>
	<source>
		<database>Unknown</database>
	</source>
	<size>
		<width>1420</width>
		<height>776</height>
		<depth>3</depth>
	</size>
	<segmented>0</segmented>
	<object>
		<name>Berlaku Hingga</name>
		<pose>Unspecified</pose>
		<truncated>0</truncated>
		<difficult>0</difficult>
		<bndbox>
			<xmin>434</xmin>
			<ymin>603</ymin>
			<xmax>639</xmax>
			<ymax>650</ymax>
		</bndbox>
	</object>
	<object>
		<name>Berlaku Hingga</name>
		<pose>Unspecified</pose>
		<truncated>0</truncated>
		<difficult>0</difficult>
		<bndbox>
			<xmin>640</xmin>
			<ymin>602</ymin>
			<xmax>789</xmax>
			<ymax>643</ymax>
		</bndbox>
	</object>
</annotation>
