<annotation><filename>1b64a597eb674c15873e88e987d78ec8.jpg.jpg</filename><path>/home/huyvd/Documents/works/pytorch_tutorial/tap_code/indo_card_code/card_indo_test_step3/save_img/1b64a597eb674c15873e88e987d78ec8.jpg.jpg</path><source><database>Unknown</database></source><size><width>982</width><height>523</height></size><object>
		<name>Alamat</name>
		<pose>Unspecified</pose>
		<truncated>0</truncated>
		<difficult>0</difficult>
		<bndbox>
			<xmin>257</xmin>
			<ymin>202</ymin>
			<xmax>347</xmax>
			<ymax>227</ymax>
		</bndbox>
	</object>
	<object>
		<name>Alamat</name>
		<pose>Unspecified</pose>
		<truncated>0</truncated>
		<difficult>0</difficult>
		<bndbox>
			<xmin>343</xmin>
			<ymin>204</ymin>
			<xmax>435</xmax>
			<ymax>225</ymax>
		</bndbox>
	</object>
	<object>
		<name>Alamat</name>
		<pose>Unspecified</pose>
		<truncated>0</truncated>
		<difficult>0</difficult>
		<bndbox>
			<xmin>429</xmin>
			<ymin>201</ymin>
			<xmax>488</xmax>
			<ymax>227</ymax>
		</bndbox>
	</object>
	<segmented>0</segmented></annotation>