<annotation><filename>74c54232f7c44647abda6513a25c4069.jpg.jpg</filename><path>/home/huyvd/Documents/works/pytorch_tutorial/tap_code/indo_card_code/card_indo_test_step3/save_img/74c54232f7c44647abda6513a25c4069.jpg.jpg</path><source><database>Unknown</database></source><size><width>1222</width><height>673</height></size><object>
		<name>Alamat</name>
		<pose>Unspecified</pose>
		<truncated>0</truncated>
		<difficult>0</difficult>
		<bndbox>
			<xmin>341</xmin>
			<ymin>290</ymin>
			<xmax>577</xmax>
			<ymax>324</ymax>
		</bndbox>
	</object>
	<object>
		<name>Alamat</name>
		<pose>Unspecified</pose>
		<truncated>0</truncated>
		<difficult>0</difficult>
		<bndbox>
			<xmin>579</xmin>
			<ymin>293</ymin>
			<xmax>719</xmax>
			<ymax>331</ymax>
		</bndbox>
	</object>
	<object>
		<name>Alamat</name>
		<pose>Unspecified</pose>
		<truncated>0</truncated>
		<difficult>0</difficult>
		<bndbox>
			<xmin>715</xmin>
			<ymin>299</ymin>
			<xmax>819</xmax>
			<ymax>329</ymax>
		</bndbox>
	</object>
	<object>
		<name>Alamat</name>
		<pose>Unspecified</pose>
		<truncated>0</truncated>
		<difficult>0</difficult>
		<bndbox>
			<xmin>334</xmin>
			<ymin>326</ymin>
			<xmax>696</xmax>
			<ymax>364</ymax>
		</bndbox>
	</object>
	<segmented>0</segmented></annotation>