<annotation><filename>abf8331103804b0aa6d79d42c91aab7d.jpg.jpg</filename><path>/home/huyvd/Documents/works/pytorch_tutorial/tap_code/indo_card_code/card_indo_test_step3/save_img/abf8331103804b0aa6d79d42c91aab7d.jpg.jpg</path><source><database>Unknown</database></source><size><width>1084</width><height>622</height></size><object>
		<name>Alamat</name>
		<pose>Unspecified</pose>
		<truncated>0</truncated>
		<difficult>0</difficult>
		<bndbox>
			<xmin>292</xmin>
			<ymin>249</ymin>
			<xmax>455</xmax>
			<ymax>275</ymax>
		</bndbox>
	</object>
	<object>
		<name>Alamat</name>
		<pose>Unspecified</pose>
		<truncated>0</truncated>
		<difficult>0</difficult>
		<bndbox>
			<xmin>452</xmin>
			<ymin>247</ymin>
			<xmax>562</xmax>
			<ymax>272</ymax>
		</bndbox>
	</object>
	<object>
		<name>Alamat</name>
		<pose>Unspecified</pose>
		<truncated>0</truncated>
		<difficult>0</difficult>
		<bndbox>
			<xmin>560</xmin>
			<ymin>245</ymin>
			<xmax>767</xmax>
			<ymax>274</ymax>
		</bndbox>
	</object>
	<segmented>0</segmented></annotation>