<annotation><filename>503cd6a80f5c4949846437ba9a0be6f8.jpg.jpg</filename><path>/home/huyvd/Documents/works/pytorch_tutorial/tap_code/indo_card_code/card_indo_test_step3/save_img/503cd6a80f5c4949846437ba9a0be6f8.jpg.jpg</path><source><database>Unknown</database></source><size><width>1420</width><height>776</height></size><object>
		<name>Nama</name>
		<pose>Unspecified</pose>
		<truncated>0</truncated>
		<difficult>0</difficult>
		<bndbox>
			<xmin>415</xmin>
			<ymin>186</ymin>
			<xmax>556</xmax>
			<ymax>226</ymax>
		</bndbox>
	</object>
	<object>
		<name>Nama</name>
		<pose>Unspecified</pose>
		<truncated>0</truncated>
		<difficult>0</difficult>
		<bndbox>
			<xmin>556</xmin>
			<ymin>190</ymin>
			<xmax>595</xmax>
			<ymax>224</ymax>
		</bndbox>
	</object>
	<object>
		<name>Nama</name>
		<pose>Unspecified</pose>
		<truncated>0</truncated>
		<difficult>0</difficult>
		<bndbox>
			<xmin>599</xmin>
			<ymin>184</ymin>
			<xmax>863</xmax>
			<ymax>224</ymax>
		</bndbox>
	</object>
	<segmented>0</segmented></annotation>