<annotation>
	<folder>save_img</folder>
	<filename>db57fec86dc946428f8b478d4b94abb2.jpg.jpg</filename>
	<path>/home/huyvd/Documents/works/pytorch_tutorial/tap_code/indo_card_code/card_indo_test_step3/save_img/db57fec86dc946428f8b478d4b94abb2.jpg.jpg</path>
	<source>
		<database>Unknown</database>
	</source>
	<size>
		<width>586</width>
		<height>325</height>
		<depth>3</depth>
	</size>
	<segmented>0</segmented>
	<object>
		<name>Status Perkawinan</name>
		<pose>Unspecified</pose>
		<truncated>0</truncated>
		<difficult>0</difficult>
		<bndbox>
			<xmin>145</xmin>
			<ymin>230</ymin>
			<xmax>198</xmax>
			<ymax>247</ymax>
		</bndbox>
	</object>
	<object>
		<name>Status Perkawinan</name>
		<pose>Unspecified</pose>
		<truncated>0</truncated>
		<difficult>0</difficult>
		<bndbox>
			<xmin>198</xmin>
			<ymin>231</ymin>
			<xmax>253</xmax>
			<ymax>245</ymax>
		</bndbox>
	</object>
</annotation>
